Workbook

Sheet basic 2
A1: Id | B1: Name | C1: Price | D1: Stock | E1: Investment
A2: 1 | B2: PC | C2: 38000 | D2: 12 | E2: =PRODUCT(C2:D2) -> 456000
A3: 2 | B3: Cycle | C3: 7000 | D3: 25 | E3: =PRODUCT(C3:D3) -> 175000
A4: 3 | B4: Mobile | C4: 13000 | D4: 50 | E4: =PRODUCT(C4:D4) -> 650000
A5: 4 | B5: Laptop | C5: 45000 | D5: 32 | E5: =PRODUCT(C5:D5) -> 1440000
A6: 5 | B6: Bag | C6: 560 | D6: 90 | E6: =PRODUCT(C6:D6) -> 50400
A7: 6 | B7: Watch | C7: 1200 | D7: 48 | E7: =PRODUCT(C7:D7) -> 57600
A9: Total Investment | E9: =SUM(E2:E7) -> 2829000
B10: Average Price | E10: =AVERAGE(E2:E7) -> 471500
B11: Max investment | E11: =MAX(E2:E7) -> 1440000
B12: Min Investment | E12: =MIN(E2:E7) -> 50400
B13: Count Products | E13: =COUNT(A2:A7) -> 6
B14: Count Products by name | E14: =COUNTA(B2:B7) -> 6
B15: 3rd Max | E15: =LARGE(E2:E7,3) -> 456000
B16: 2th Min

Sheet concat
A1: Sr no | B1: wing | C1: Flat No | D1: First Name | E1: Middle Name | F1: Last Name | G1: Full Name | H1: Mobile No | I1: Last 4 Digit | J1: first 4 | K1: total character
A2: I | B2: A | C2: 121 | D2: Kapil | E2: Kumar | F2: Singh | G2: Kapil Kumar Singh | I2: =RIGHT(H2,4) | J2: =LEFT(H2,4) | K2: =LEN(G2) -> 17
A3: II | B3: C | C3: 564 | D3: amit | E3: Ravi | F3: Kumar | G3: Amit Ravi Kumar | H3: 5648624984 | I3: =RIGHT(H3,4) -> 4984 | J3: =LEFT(H3,4) -> 5648 | K3: =LEN(G3) -> 15
A4: III | B4: S | C4: 25 | D4: Sumit | E4: deepak | F4: Patel | G4: Sumit Deepak Patel | H4: 9656569964 | I4: =RIGHT(H4,4) -> 9964 | J4: =LEFT(H4,4) -> 9656 | K4: =LEN(G4) -> 18
A5: IV | B5: C | C5: 561 | D5: aman | E5: Dipu | F5: verma | G5: Aman Dipu Verma | H5: 5625468464 | I5: =RIGHT(H5,4) -> 8464 | J5: =LEFT(H5,4) -> 5625 | K5: =LEN(G5) -> 15
D9: =_xlfn.CONCAT(D2, " ",E2, " ",F2) -> Kapil Kumar Singh

Sheet Sheet2
A1: Flat no | B1: First name | C1: Middle name | D1: Last name | E1: Full name
A2: B 45 | B2: sumit | C2: depu | D2: patel
A3: C 65 | B3: amiy | C3: Sonu | D3: verma
B8: date | C8: year | D8: month | E8: date
B9: 45443 | C9: =DATEDIF(B9,TODAY(),"Y") -> 2 | D9: =DATEDIF(B9,TODAY(),"YM") -> 2 | E9: =DATEDIF(B9,TODAY(),"MD") -> 6

Sheet Sheet3
A2: Roll no | B2: Name | C2: Percentage | D2: Attendance | E2: Pass/Fail | F2: Scholarship | G2: Gift | H2: admit card
A3: 1 | B3: Amit | C3: 45 | D3: 80 | E3: =IF(C3>35,"Pass","Fail") -> Pass | F3: =AND(C3>80,D3>85) -> FALSE | G3: =OR(C3>60,D3>75) -> TRUE | H3: =IF(AND(C3>50,D3>60),"yes","no") -> no
A4: 2 | B4: Sumit | C4: 32 | D4: 55 | E4: =IF(C4>35,"Pass","Fail") -> Fail | F4: =AND(C4>80,D4>85) -> FALSE | G4: =OR(C4>60,D4>75) -> FALSE | H4: =IF(AND(C4>50,D4>60),"yes","no") -> no
A5: 3 | B5: Aman | C5: 82 | D5: 95 | E5: =IF(C5>35,"Pass","Fail") -> Pass | F5: =AND(C5>80,D5>85) -> TRUE | G5: =OR(C5>60,D5>75) -> TRUE | H5: =IF(AND(C5>50,D5>60),"yes","no") -> yes
B9: A | C9: B | D9: C
B10: 10 | C10: 5 | D10: =IFERROR(B10/C10,"not avvailable") -> 2
B11: 15 | C11: 3 | D11: =IFERROR(B11/C11,"not avvailable") -> 5
B12: 25 | C12: 0 | D12: =IFERROR(B12/C12,"not avvailable") -> not avvailable
B13: 10 | C13: 0 | D13: =IFERROR(B13/C13,"not avvailable") -> not avvailable

Sheet Sheet4
A3: Name | B3: 46235 | C3: 46236 | D3: 46237 | E3: Present Days | F3: Absent Days | G3: Total Days | H3: percentage
A4: amit | B4: P | C4: P | D4: P | E4: =COUNTIF(B4:D4,"P") -> 3 | F4: =COUNTIF(B4:D4,"A") -> 0 | G4: =COUNTA(B4:D4) -> 3 | H4: =(E4/G4)*100 -> 100
A5: sumit | B5: A | C5: P | D5: P | E5: =COUNTIF(B5:D5,"P") -> 2 | F5: =COUNTIF(B5:D5,"A") -> 1 | G5: =COUNTA(B5:D5) -> 3 | H5: =(E5/G5)*100 -> 66.666667
A6: aman | B6: P | C6: P | D6: A | E6: =COUNTIF(B6:D6,"P") -> 2 | F6: =COUNTIF(B6:D6,"A") -> 1 | G6: =COUNTA(B6:D6) -> 3 | H6: =(E6/G6)*100 -> 66.666667

Sheet Sheet5
A1: ID | B1: NAME | C1: JOINING DATE | D1: YEAR | E1: MONTH | F1: DAY | G1: TODAY | H1: now | I1: day | J1: MONTH | K1: YEAR | L1: DOB | M1: HOUR | N1: MINUTE | O1: TIME
A2: 101 | B2: AMIT | C2: 45102 | D2: =YEAR(C2) -> 2023 | E2: =MONTH(C2) -> 6 | F2: =DAY(C2) -> 25 | G2: =TODAY() -> 46240 | H2: =NOW() -> 46240.398 | I2: 2 | J2: 11 | K2: 2001 | L2: =DATE(K2,J2,I2) -> 37197 | M2: 20 | N2: 45 | O2: =TIME(M2,N2,0) -> 0.86458333
C7: year difference | D7: year difference | E7: month diff | F7: day if
C8: =DATEDIF(C2,G2,"Y") -> 3 | D8: =DATEDIF(C2,TODAY(),"M") -> 37 | E8: =DATEDIF(C2,TODAY(),"YM") -> 1 | F8: =DATEDIF(C2,TODAY(),"MD") -> 12

Sheet practice 1
A1: Order ID | B1: Salesperson | C1: Product | D1: Region | E1: Month | F1: Qty | G1: Amount
A2: 1001 | B2: Amit | C2: Laptop | D2: North | E2: Jan | F2: 2 | G2: 100000
A3: 1002 | B3: Priya | C3: Mouse | D3: South | E3: Jan | F3: 10 | G3: 10000
A4: 1003 | B4: Amit | C4: Laptop | D4: West | E4: Feb | F4: 1 | G4: 50000
A5: 1004 | B5: Rahul | C5: Keyboard | D5: North | E5: Jan | F5: 5 | G5: 15000
A6: 1005 | B6: Priya | C6: Laptop | D6: South | E6: Feb | F6: 3 | G6: 150000
A7: 1006 | B7: Amit | C7: Mouse | D7: North | E7: Mar | F7: 8 | G7: 8000
A8: 1007 | B8: Rahul | C8: Laptop | D8: West | E8: Feb | F8: 2 | G8: 100000 | J8: 9. Find the total quantity sold by Priya in South Region during February.
A9: 1008 | B9: Amit | C9: Keyboard | D9: South | E9: Jan | F9: 4 | G9: 12000 | J9: =SUMIFS(F2:F11,B2:B11,"priya",D2:D11,"south",E2:E11,"feb") -> 3
A10: 1009 | B10: Priya | C10: Mouse | D10: North | E10: Mar | F10: 6 | G10: 6000 | J10: 10. Find the total sales where Quantity is less than 3.
A11: 1010 | B11: Rahul | C11: Laptop | D11: North | E11: Mar | F11: 1 | G11: 50000 | J11: =SUMIF(F2:F11,">3",G2:G11) -> 51000
H15: 4. How many Mouse orders were sold in March?
A16: 1. How many Laptop orders were sold? | H16: =SUMIFS(F2:F11,C2:C11,"mouse") -> 24
A17: =SUMIFS(F2:F11,C2:C11,"laptop") -> 9 | H17: 5. How many orders have Quantity greater than 5?
H18: =COUNTIF(F2:F11,">5") -> 3
A19: 2. How many Laptop orders were sold in North Region? | H19: 6.How many Laptop orders have Amount greater than ₹80,000?
A20: =SUMIFS(F2:F11,C2:C11,"laptop",D2:D11,"north") -> 3 | B20: =COUNTIFS(C2:C11,"Laptop",D2:D11,"North") -> 2 | H20: =COUNTIFS(C2:C11,"laptop",G2:G11,">80000") -> 3
A21: 3. How many orders did Amit receive in January | H21: 7. Find the total sales where Amount is greater than ₹50,000
A22: =COUNTIFS(B2:B11,"amit",E2:E11,"jan") -> 2 | H22: =SUMIF(G2:G11,">50000") -> 350000
A23: 11. Find total sales based on selected Salesperson, Product, Region, and Month. | H23: 8. Find the total sales excluding North Region.
A24: salesperson | C24: product | D24: region | E24: month
A25: Priya | C25: Mouse | D25: South | E25: Jan | H25: =SUMIF(D2:D11,"<>north",G2:G11) -> 322000
A26: total sales | C26: =SUMIFS(G2:G11,B2:B11,A25,C2:C11,C25,D2:D11,D25,E2:E11,E25) -> 10000
A27: total qty | C27: =SUMIFS(F2:F11,B2:B11,A25,C2:C11,C25,D2:D11,D25,E2:E11,E25) -> 10
A28: total order | C28: =COUNTIFS(B2:B11,A25,C2:C11,C25,D2:D11,D25,E2:E11,E25) -> 1

Sheet data validtion
A1: Order ID | B1: Salesperson | C1: Product | D1: Region | E1: Month | F1: Qty | G1: Amount
A2: All | B2: All | C2: All | D2: All | E2: All | F2: All | G2: All
A3: 1001 | B3: Amit | C3: Laptop | D3: North | E3: Jan | F3: 2 | G3: 100000
A4: 1002 | B4: Priya | C4: Mouse | D4: South | E4: Jan | F4: 10 | G4: 10000
A5: 1003 | B5: Amit | C5: Laptop | D5: West | E5: Feb | F5: 1 | G5: 50000
A6: 1004 | B6: Rahul | C6: Keyboard | D6: North | E6: Jan | F6: 5 | G6: 15000
A7: 1005 | B7: Priya | C7: Laptop | D7: South | E7: Feb | F7: 3 | G7: 150000
A8: 1006 | B8: Amit | C8: Mouse | D8: North | E8: Mar | F8: 8 | G8: 8000
A9: 1007 | B9: Rahul | C9: Laptop | D9: West | E9: Feb | F9: 2 | G9: 100000
A10: 1008 | B10: Amit | C10: Keyboard | D10: South | E10: Jan | F10: 4 | G10: 12000
A11: 1009 | B11: Priya | C11: Mouse | D11: North | E11: Mar | F11: 6 | G11: 6000
A12: 1010 | B12: Rahul | C12: Laptop | D12: North | E12: Mar | F12: 1 | G12: 50000
E15: Salesperson | F15: Product | G15: Region | H15: Month
E16: All | F16: Laptop | G16: All | H16: All
D17: Total revenue | E17: =SUMIFS(G2:G12,B2:B12,IF(E16="All","*",E16),C2:C12,IF(F16="All","*",F16),D2:D12,IF(G16="All","*",G16),E2:E12,IF(H16="All","*",H16)) -> 450000
D19: Total Order | E19: =COUNTIFS(B2:B12,IF(E16="All","*",E16),C2:C12,IF(F16="All","*",F16),D2:D12,IF(G16="All","*",G16),E2:E12,IF(H16="All","*",H16)) -> 5
D21: Total Quantity | E21: =SUMIFS(F2:F12,B2:B12,IF(E16="All","*",E16),C2:C12,IF(F16="All","*",F16),D2:D12,IF(G16="All","*",G16),E2:E12,IF(H16="All","*",H16)) -> 9

Sheet Sheet1
A2: ID | B2: Name | C2: Department | D2: Joining Date | E2: Salary | G2: COURSE FEE
A3: 101 | B3: Amiy | C3: HR | D3: 45414 | E3: =VLOOKUP(Sheet1!A3,Sheet6!$A$2:$B$6,2,FALSE) -> 25000 | G3: =VLOOKUP(A3,Sheet7!$A$2:$B$6,2) -> 35000
A4: 102 | B4: Piyush | C4: Designing | D4: 45211 | E4: =VLOOKUP(Sheet1!A4,Sheet6!$A$2:$B$6,2,FALSE) -> 30000 | G4: =VLOOKUP(A4,Sheet7!$A$2:$B$6,2) -> 15000
A5: 103 | B5: Aman | C5: IT | D5: 45874 | E5: =VLOOKUP(Sheet1!A5,Sheet6!$A$2:$B$6,2,FALSE) -> 35000 | G5: =VLOOKUP(A5,Sheet7!$A$2:$B$6,2) -> 20000
A6: 104 | B6: Sonu | C6: IT | D6: 30-02-2026 | E6: =VLOOKUP(Sheet1!A6,Sheet6!$A$2:$B$6,2,FALSE) -> 28000 | G6: =VLOOKUP(A6,Sheet7!$A$2:$B$6,2) -> 25000
A7: 105 | B7: Monu | C7: Assisstant | D7: 45580 | E7: =VLOOKUP(Sheet1!A7,Sheet6!$A$2:$B$6,2,FALSE) -> 22000 | G7: =VLOOKUP(A7,Sheet7!$A$2:$B$6,2) -> 10000

Sheet Sheet6
A1: ID | B1: SALARY
A2: 105 | B2: 22000
A3: 102 | B3: 30000
A4: 103 | B4: 35000
A5: 104 | B5: 28000
A6: 101 | B6: 25000

Sheet Sheet7
A1: ID | B1: FEES | C1: COURSE NAME
A2: 101 | B2: 35000 | C2: Data Analytics
A3: 102 | B3: 15000 | C3: Digital Print
A4: 103 | B4: 20000 | C4: Marketing
A5: 104 | B5: 25000 | C5: Security
A6: 105 | B6: 10000 | C6: Tally
